LICENSE
hashtools/__init__.py
hashtools/__main__.py
hashtools/py.typed
python_hashtools-0.0.5.dist-info/LICENSE
python_hashtools-0.0.5.dist-info/METADATA
python_hashtools-0.0.5.dist-info/WHEEL
python_hashtools-0.0.5.dist-info/entry_points.txt
python_hashtools-0.0.5.dist-info/RECORD
